LICENSE
MANIFEST.in
README.md
setup.py
axortvypei/__init__.py
axortvypei/api_helper.py
axortvypei/axortvypei_client.py
axortvypei/configuration.py
axortvypei/decorators.py
axortvypei.egg-info/PKG-INFO
axortvypei.egg-info/SOURCES.txt
axortvypei.egg-info/dependency_links.txt
axortvypei.egg-info/requires.txt
axortvypei.egg-info/top_level.txt
axortvypei/controllers/__init__.py
axortvypei/controllers/api_controller.py
axortvypei/controllers/base_controller.py
axortvypei/exceptions/__init__.py
axortvypei/exceptions/api_exception.py
axortvypei/http/__init__.py
axortvypei/http/http_call_back.py
axortvypei/http/http_client.py
axortvypei/http/http_context.py
axortvypei/http/http_method_enum.py
axortvypei/http/http_request.py
axortvypei/http/http_response.py
axortvypei/http/requests_client.py
axortvypei/http/auth/__init__.py
axortvypei/http/auth/basic_auth.py
axortvypei/models/__init__.py
axortvypei/models/suite_code_enum.py
tests/__init__.py
tests/http_response_catcher.py
tests/test_helper.py
tests/controllers/__init__.py
tests/controllers/controller_test_base.py
tests/controllers/test_api_controller.py